nngpr/__init__.py
nngpr/base_nngpr.py
nngpr/batched_kernels.py
nngpr/cuda_kernel_accelerators.py
nngpr/cupy_nngpr.py
nngpr/numpy_nngpr.py
nngpr/run_tests.py
nngpr/torch_nngpr.py
nngpr/test/__init__.py
nngpr/test/nngpr_base_tester.py
nngpr/test/test_batched_kernels.py
nngpr/test/test_cupy_nngpr.py
nngpr/test/test_numpy_nngpr.py
nngpr/test/test_torch_nngpr.py
nngpr-0.1.0.dist-info/licenses/LICENSE
nngpr-0.1.0.dist-info/METADATA
nngpr-0.1.0.dist-info/WHEEL
nngpr-0.1.0.dist-info/top_level.txt
nngpr-0.1.0.dist-info/RECORD
