Metadata-Version: 2.4
Name: nngpr
Version: 0.1.0
Summary: Nearest Neighbors Gaussian Process Regressor
Author: Nicola Dal Bianco
License:                     GNU GENERAL PUBLIC LICENSE
Project-URL: Homepage, https://github.com/stavoltafunzia/nngpr
Project-URL: Bug Tracker, https://github.com/stavoltafunzia/nngpr/issues
Classifier: Programming Language :: Python :: 3
Classifier: License :: OSI Approved :: GNU General Public License v3 (GPLv3)
Classifier: Operating System :: OS Independent
Requires-Python: >=3.11
License-File: LICENSE
Requires-Dist: numpy>=2.0
Requires-Dist: scipy>=1.15
Requires-Dist: scikit-learn>=1.6
Provides-Extra: cupy
Requires-Dist: cupy-cuda12x>=13.4; extra == "cupy"
Provides-Extra: torch
Requires-Dist: torch>=2.7; extra == "torch"
Requires-Dist: cupy-cuda12x>=13.4; extra == "torch"
Dynamic: license-file
